{
    "name": "Global Information",
    "numberOfRequests": {
        "total": 2,
        "ok": 0,
        "ko": 2
    },
    "minResponseTime": {
        "total": 197,
        "ok": 0,
        "ko": 197
    },
    "maxResponseTime": {
        "total": 3916,
        "ok": 0,
        "ko": 3916
    },
    "meanResponseTime": {
        "total": 2057,
        "ok": 0,
        "ko": 2057
    },
    "standardDeviation": {
        "total": 1860,
        "ok": 0,
        "ko": 1860
    },
    "percentiles1": {
        "total": 2057,
        "ok": 0,
        "ko": 2057
    },
    "percentiles2": {
        "total": 2986,
        "ok": 0,
        "ko": 2986
    },
    "percentiles3": {
        "total": 3730,
        "ok": 0,
        "ko": 3730
    },
    "percentiles4": {
        "total": 3879,
        "ok": 0,
        "ko": 3879
    },
    "group1": {
    "name": "t < 800 ms",
    "count": 0,
    "percentage": 0
},
    "group2": {
    "name": "800 ms < t < 1200 ms",
    "count": 0,
    "percentage": 0
},
    "group3": {
    "name": "t > 1200 ms",
    "count": 0,
    "percentage": 0
},
    "group4": {
    "name": "failed",
    "count": 2,
    "percentage": 100
},
    "meanNumberOfRequestsPerSecond": {
        "total": 0.25,
        "ok": 0,
        "ko": 0.25
    }
}