{
    "name": "Global Information",
    "numberOfRequests": {
        "total": 11384,
        "ok": 11384,
        "ko": 0
    },
    "minResponseTime": {
        "total": 187,
        "ok": 187,
        "ko": 0
    },
    "maxResponseTime": {
        "total": 2809,
        "ok": 2809,
        "ko": 0
    },
    "meanResponseTime": {
        "total": 225,
        "ok": 225,
        "ko": 0
    },
    "standardDeviation": {
        "total": 106,
        "ok": 106,
        "ko": 0
    },
    "percentiles1": {
        "total": 213,
        "ok": 213,
        "ko": 0
    },
    "percentiles2": {
        "total": 221,
        "ok": 221,
        "ko": 0
    },
    "percentiles3": {
        "total": 239,
        "ok": 239,
        "ko": 0
    },
    "percentiles4": {
        "total": 926,
        "ok": 926,
        "ko": 0
    },
    "group1": {
    "name": "t < 800 ms",
    "count": 11230,
    "percentage": 99
},
    "group2": {
    "name": "800 ms < t < 1200 ms",
    "count": 137,
    "percentage": 1
},
    "group3": {
    "name": "t > 1200 ms",
    "count": 17,
    "percentage": 0
},
    "group4": {
    "name": "failed",
    "count": 0,
    "percentage": 0
},
    "meanNumberOfRequestsPerSecond": {
        "total": 206.98181818181817,
        "ok": 206.98181818181817,
        "ko": 0
    }
}